flask_firebase_admin/__init__.py
flask_firebase_admin/__version__.py
flask_firebase_admin/flask_firebase_admin.py
flask_firebase_admin/status_codes.py
flask_firebase_admin-0.2.3.dist-info/LICENSE
flask_firebase_admin-0.2.3.dist-info/WHEEL
flask_firebase_admin-0.2.3.dist-info/METADATA
flask_firebase_admin-0.2.3.dist-info/RECORD
