Metadata-Version: 2.1
Name: flask-firebase-admin
Version: 0.2.3
Summary: Firebase for Flask
Home-page: https://github.com/andrewrosss/flask-firebase-admin
License: MIT
Keywords: flask,firebase,admin,auth
Author: Andrew Ross
Author-email: andrew.ross.mail@gmail.com
Requires-Python: >=3.7,<4.0
Classifier: Development Status :: 4 - Beta
Classifier: Environment :: Web Environment
Classifier: Framework :: Flask
Classifier: Intended Audience :: Developers
Classifier: License :: OSI Approved :: MIT License
Classifier: Operating System :: OS Independent
Classifier: Programming Language :: Python :: 3
Classifier: Programming Language :: Python :: 3.0
Classifier: Programming Language :: Python :: 3.7
Classifier: Programming Language :: Python :: 3.8
Classifier: Programming Language :: Python :: 3.9
Classifier: Topic :: Internet :: WWW/HTTP :: Dynamic Content
Classifier: Topic :: Software Development :: Libraries :: Python Modules
Requires-Dist: firebase-admin (>=4.0.0,<5.0.0)
Requires-Dist: flask (>=1.0.0,<2.0.0)
